bjpack/__init__.py
bjpack/ai.py
bjpack/bjack.py
bjpack/deck.py
bjpack/main.py
bjpack/turn.py
blackjackfire-1.2.1.dist-info/licenses/LICENSE
blackjackfire-1.2.1.dist-info/METADATA
blackjackfire-1.2.1.dist-info/WHEEL
blackjackfire-1.2.1.dist-info/entry_points.txt
blackjackfire-1.2.1.dist-info/top_level.txt
blackjackfire-1.2.1.dist-info/RECORD
