Metadata-Version: 2.4
Name: blackjackFire
Version: 1.2.1
Summary: A terminal-based Blackjack game
Author-email: FireShade3DS <ben042010@icloud.com>
License-Expression: MIT
Classifier: Programming Language :: Python :: 3
Classifier: Operating System :: OS Independent
Classifier: Environment :: Console
Classifier: Topic :: Games/Entertainment :: Board Games
Requires-Python: >=3.7
License-File: LICENSE
Requires-Dist: termcolor
Requires-Dist: colorama
Dynamic: license-file
